{
  "asOf": "2026-07-03T21:30:00+00:00",
  "note": "SAMPLE DATA -- replace automatically after the first GitHub Action run",
  "rows": [
    { "ticker": "AAPL", "name": "Apple Inc.", "sector": "Technology", "price": 214.32, "trailingPE": 33.1, "forwardPE": 28.4, "avgPE5y": 29.8, "signal": "above avg" },
    { "ticker": "MSFT", "name": "Microsoft Corp.", "sector": "Technology", "price": 468.90, "trailingPE": 35.6, "forwardPE": 30.2, "avgPE5y": 33.9, "signal": "in line" },
    { "ticker": "GOOGL", "name": "Alphabet Inc.", "sector": "Communication Services", "price": 189.45, "trailingPE": 24.7, "forwardPE": 21.3, "avgPE5y": 25.6, "signal": "in line" },
    { "ticker": "AMZN", "name": "Amazon.com Inc.", "sector": "Consumer Cyclical", "price": 231.10, "trailingPE": 38.9, "forwardPE": 32.1, "avgPE5y": 52.4, "signal": "below avg" },
    { "ticker": "NVDA", "name": "NVIDIA Corp.", "sector": "Technology", "price": 158.77, "trailingPE": 46.2, "forwardPE": 34.8, "avgPE5y": 60.1, "signal": "below avg" },
    { "ticker": "META", "name": "Meta Platforms Inc.", "sector": "Communication Services", "price": 712.55, "trailingPE": 27.3, "forwardPE": 23.9, "avgPE5y": 26.5, "signal": "in line" },
    { "ticker": "TSLA", "name": "Tesla Inc.", "sector": "Consumer Cyclical", "price": 298.60, "trailingPE": 88.4, "forwardPE": 71.2, "avgPE5y": 95.7, "signal": "below avg" }
  ]
}
