{
  "asOf": "2026-07-16T22:30:39.964630+00:00",
  "benchmarks": [
    {
      "ticker": "SPY",
      "name": "S&P 500 (SPY)",
      "sector": "Unknown",
      "price": 750.72,
      "trailingPE": 27.0,
      "forwardPE": null,
      "avgPE5y": null,
      "return1M": 0.53,
      "signal": "n/a"
    },
    {
      "ticker": "QQQ",
      "name": "Nasdaq 100 (QQQ)",
      "sector": "Unknown",
      "price": 705.94,
      "trailingPE": 31.33,
      "forwardPE": null,
      "avgPE5y": null,
      "return1M": -4.14,
      "signal": "n/a"
    }
  ],
  "rows": [
    {
      "ticker": "BRK-B",
      "name": "BRK-B",
      "sector": "Unknown",
      "price": 493.12,
      "trailingPE": 14.68,
      "forwardPE": 22.92,
      "avgPE5y": 11.77,
      "return1M": -1.45,
      "signal": "above avg"
    },
    {
      "ticker": "JPM",
      "name": "JPM",
      "sector": "Unknown",
      "price": 343.15,
      "trailingPE": 14.7,
      "forwardPE": 14.01,
      "avgPE5y": 8.33,
      "return1M": 5.31,
      "signal": "above avg"
    },
    {
      "ticker": "DIS",
      "name": "DIS",
      "sector": "Unknown",
      "price": 99.71,
      "trailingPE": 15.95,
      "forwardPE": 13.34,
      "avgPE5y": 17.13,
      "return1M": 3.59,
      "signal": "in line"
    },
    {
      "ticker": "PEP",
      "name": "PEP",
      "sector": "Unknown",
      "price": 139.43,
      "trailingPE": 18.25,
      "forwardPE": 15.52,
      "avgPE5y": 19.59,
      "return1M": 2.98,
      "signal": "in line"
    },
    {
      "ticker": "NKE",
      "name": "NKE",
      "sector": "Unknown",
      "price": 44.57,
      "trailingPE": 21.22,
      "forwardPE": 18.88,
      "avgPE5y": 43.15,
      "return1M": 8.57,
      "signal": "below avg"
    },
    {
      "ticker": "PG",
      "name": "PG",
      "sector": "Unknown",
      "price": 151.5,
      "trailingPE": 22.15,
      "forwardPE": 21.48,
      "avgPE5y": 21.2,
      "return1M": 3.31,
      "signal": "in line"
    },
    {
      "ticker": "MCD",
      "name": "MCD",
      "sector": "Unknown",
      "price": 273.46,
      "trailingPE": 22.54,
      "forwardPE": 19.3,
      "avgPE5y": 21.87,
      "return1M": 1.17,
      "signal": "in line"
    },
    {
      "ticker": "MSFT",
      "name": "MSFT",
      "sector": "Unknown",
      "price": 401.1,
      "trailingPE": 23.92,
      "forwardPE": 20.7,
      "avgPE5y": 21.55,
      "return1M": 7.53,
      "signal": "above avg"
    },
    {
      "ticker": "META",
      "name": "META",
      "sector": "Unknown",
      "price": 664.54,
      "trailingPE": 24.15,
      "forwardPE": 18.29,
      "avgPE5y": 15.4,
      "return1M": 17.97,
      "signal": "above avg"
    },
    {
      "ticker": "XOM",
      "name": "XOM",
      "sector": "Unknown",
      "price": 145.95,
      "trailingPE": 24.57,
      "forwardPE": 13.72,
      "avgPE5y": 16.96,
      "return1M": 6.75,
      "signal": "above avg"
    },
    {
      "ticker": "HD",
      "name": "HD",
      "sector": "Unknown",
      "price": 348.02,
      "trailingPE": 24.73,
      "forwardPE": 21.63,
      "avgPE5y": 23.07,
      "return1M": -1.32,
      "signal": "in line"
    },
    {
      "ticker": "KO",
      "name": "KO",
      "sector": "Unknown",
      "price": 84.92,
      "trailingPE": 26.7,
      "forwardPE": 24.38,
      "avgPE5y": 19.15,
      "return1M": 4.49,
      "signal": "above avg"
    },
    {
      "ticker": "GOOGL",
      "name": "GOOGL",
      "sector": "Unknown",
      "price": 354.46,
      "trailingPE": 27.08,
      "forwardPE": 24.25,
      "avgPE5y": 13.29,
      "return1M": -0.81,
      "signal": "above avg"
    },
    {
      "ticker": "JNJ",
      "name": "JNJ",
      "sector": "Unknown",
      "price": 249.97,
      "trailingPE": 29.0,
      "forwardPE": 19.51,
      "avgPE5y": 18.92,
      "return1M": -1.57,
      "signal": "above avg"
    },
    {
      "ticker": "AMZN",
      "name": "AMZN",
      "sector": "Unknown",
      "price": 249.89,
      "trailingPE": 29.89,
      "forwardPE": 25.23,
      "avgPE5y": 20.64,
      "return1M": 4.85,
      "signal": "above avg"
    },
    {
      "ticker": "NVDA",
      "name": "NVDA",
      "sector": "Unknown",
      "price": 207.4,
      "trailingPE": 31.81,
      "forwardPE": 16.2,
      "avgPE5y": 13.63,
      "return1M": 3.65,
      "signal": "above avg"
    },
    {
      "ticker": "V",
      "name": "V",
      "sector": "Unknown",
      "price": 365.14,
      "trailingPE": 31.83,
      "forwardPE": 24.56,
      "avgPE5y": 23.28,
      "return1M": 6.43,
      "signal": "above avg"
    },
    {
      "ticker": "MA",
      "name": "MA",
      "sector": "Unknown",
      "price": 551.54,
      "trailingPE": 31.9,
      "forwardPE": 24.2,
      "avgPE5y": 25.32,
      "return1M": 7.57,
      "signal": "above avg"
    },
    {
      "ticker": "UNH",
      "name": "UNH",
      "sector": "Unknown",
      "price": 423.38,
      "trailingPE": 31.91,
      "forwardPE": 19.92,
      "avgPE5y": 33.06,
      "return1M": 1.86,
      "signal": "in line"
    },
    {
      "ticker": "CVX",
      "name": "CVX",
      "sector": "Unknown",
      "price": 183.86,
      "trailingPE": 32.03,
      "forwardPE": 14.67,
      "avgPE5y": 24.71,
      "return1M": 10.92,
      "signal": "above avg"
    },
    {
      "ticker": "AAPL",
      "name": "AAPL",
      "sector": "Unknown",
      "price": 333.26,
      "trailingPE": 40.4,
      "forwardPE": 34.64,
      "avgPE5y": 24.14,
      "return1M": 15.17,
      "signal": "above avg"
    },
    {
      "ticker": "WMT",
      "name": "WMT",
      "sector": "Unknown",
      "price": 114.95,
      "trailingPE": 40.48,
      "forwardPE": 34.98,
      "avgPE5y": 24.81,
      "return1M": 1.49,
      "signal": "above avg"
    },
    {
      "ticker": "COST",
      "name": "COST",
      "sector": "Unknown",
      "price": 945.57,
      "trailingPE": 47.54,
      "forwardPE": 41.75,
      "avgPE5y": 35.65,
      "return1M": 1.08,
      "signal": "above avg"
    },
    {
      "ticker": "ABBV",
      "name": "ABBV",
      "sector": "Unknown",
      "price": 254.39,
      "trailingPE": 124.09,
      "forwardPE": 15.63,
      "avgPE5y": 78.16,
      "return1M": 1.81,
      "signal": "above avg"
    },
    {
      "ticker": "TSLA",
      "name": "TSLA",
      "sector": "Unknown",
      "price": 391.06,
      "trailingPE": 355.51,
      "forwardPE": 153.11,
      "avgPE5y": 263.54,
      "return1M": -7.02,
      "signal": "above avg"
    }
  ]
}